README.md
setup.py
wrap_connection/__init__.py
wrap_connection/wrap_connection.py
wrap_connection.egg-info/PKG-INFO
wrap_connection.egg-info/SOURCES.txt
wrap_connection.egg-info/dependency_links.txt
wrap_connection.egg-info/top_level.txt