Metadata-Version: 2.1
Name: wrap-connection
Version: 2.0.0.0
Summary: Easily wrap connections and cursors by using decorators.
Home-page: https://github.com/victorwss/wrap-connection
Author: Victor Williams Stafusa da Silva
Author-email: victorwssilva@gmail.com
License: UNKNOWN
Platform: UNKNOWN
Classifier: Programming Language :: Python :: 3
Classifier: License :: OSI Approved :: MIT License
Classifier: Operating System :: OS Independent
